konvertek/__init__.py
konvertek/ffmpeg_handler.py
konvertek/main.py
konvertek/parsing.py
konvertek/process.py
konvertek/progress_handler.py
konvertek-0.1.3.dist-info/LICENSE
konvertek-0.1.3.dist-info/METADATA
konvertek-0.1.3.dist-info/WHEEL
konvertek-0.1.3.dist-info/entry_points.txt
konvertek-0.1.3.dist-info/top_level.txt
konvertek-0.1.3.dist-info/RECORD
