Metadata-Version: 2.1
Name: konvertek
Version: 0.1.3
Summary: Convert media. 
Author-email: The220th <The220th@gmail.com>
Project-URL: Homepage, https://github.com/The220th/konvertek
Project-URL: Issues, https://github.com/The220th/konvertek/issues
Classifier: Programming Language :: Python :: 3
Classifier: License :: OSI Approved :: MIT License
Classifier: Operating System :: OS Independent
Requires-Python: >=3.7
License-File: LICENSE
Requires-Dist: ksupk
Requires-Dist: argparse
Requires-Dist: ffmpeg-python
Requires-Dist: tqdm
